modethirteen/mkdocs/__init__.py
modethirteen/mkdocs/metadata/__init__.py
mkdocs_techdocs_modethirteen_plugins-0.1.4.dist-info/METADATA
mkdocs_techdocs_modethirteen_plugins-0.1.4.dist-info/WHEEL
mkdocs_techdocs_modethirteen_plugins-0.1.4.dist-info/entry_points.txt
mkdocs_techdocs_modethirteen_plugins-0.1.4.dist-info/licenses/LICENSE
mkdocs_techdocs_modethirteen_plugins-0.1.4.dist-info/RECORD
