Metadata-Version: 2.4
Name: mkdocs-techdocs-modethirteen-plugins
Version: 0.1.4
Summary: A collection of MkDocs plugins designed to work with Spotify's TechDocs system
Author-email: James Andrew Vaughn <jamesvaughn@modethirteen.com>
License-File: LICENSE
Requires-Dist: mkdocs
